{"otherData":{},"traceEvents":[{"cat":"function","dur":77506,"name":"glfwCreateWindow","ph":"X","pid":0,"tid":1130835890,"ts":41942004249},{"cat":"function","dur":3743,"name":"void __cdecl Hazel::OpenGLContext::Init(void)","ph":"X","pid":0,"tid":1130835890,"ts":41942081910},{"cat":"function","dur":208469,"name":"void __cdecl Hazel::WindowsWindow::Init(const struct Hazel::WindowProps &)","ph":"X","pid":0,"tid":1130835890,"ts":41941877246},{"cat":"function","dur":208492,"name":"__cdecl Hazel::WindowsWindow::WindowsWindow(const struct Hazel::WindowProps &)","ph":"X","pid":0,"tid":1130835890,"ts":41941877245},{"cat":"function","dur":29,"name":"__cdecl Hazel::OpenGLVertexArray::OpenGLVertexArray(void)","ph":"X","pid":0,"tid":1130835890,"ts":41942085785},{"cat":"function","dur":35,"name":"__cdecl Hazel::OpenGLVertexBuffer::OpenGLVertexBuffer(unsigned int)","ph":"X","pid":0,"tid":1130835890,"ts":41942085850},{"cat":"function","dur":1,"name":"void __cdecl Hazel::OpenGLVertexBuffer::Bind(void) const","ph":"X","pid":0,"tid":1130835890,"ts":41942085929},{"cat":"function","dur":34,"name":"void __cdecl Hazel::OpenGLVertexArray::AddVertexBuffer(const class std::shared_ptr<class Hazel::VertexBuffer> &)","ph":"X","pid":0,"tid":1130835890,"ts":41942085927},{"cat":"function","dur":206,"name":"__cdecl Hazel::OpenGLIndexBuffer::OpenGLIndexBuffer(unsigned int *,unsigned int)","ph":"X","pid":0,"tid":1130835890,"ts":41942086598},{"cat":"function","dur":0,"name":"void __cdecl Hazel::OpenGLIndexBuffer::Bind(void) const","ph":"X","pid":0,"tid":1130835890,"ts":41942086839},{"cat":"function","dur":22,"name":"__cdecl Hazel::OpenGLTexture2D::OpenGLTexture2D(unsigned int,unsigned int)","ph":"X","pid":0,"tid":1130835890,"ts":41942086875},{"cat":"function","dur":9,"name":"void __cdecl Hazel::OpenGLTexture2D::SetData(void *,unsigned int)","ph":"X","pid":0,"tid":1130835890,"ts":41942086922},{"cat":"function","dur":102,"name":"class std::basic_string<char,struct std::char_traits<char>,class std::allocator<char> > __cdecl Hazel::OpenGLShader::ReadFile(const class std::basic_string<char,struct std::char_traits<char>,class std::allocator<char> > &)","ph":"X","pid":0,"tid":1130835890,"ts":41942086958},{"cat":"function","dur":24,"name":"class std::unordered_map<unsigned int,class std::basic_string<char,struct std::char_traits<char>,class std::allocator<char> >,struct std::hash<unsigned int>,struct std::equal_to<unsigned int>,class std::allocator<struct std::pair<unsigned int const ,class std::basic_string<char,struct std::char_traits<char>,class std::allocator<char> > > > > __cdecl Hazel::OpenGLShader::PreProcess(const class std::basic_string<char,struct std::char_traits<char>,class std::allocator<char> > &)","ph":"X","pid":0,"tid":1130835890,"ts":41942087088},{"cat":"function","dur":32209,"name":"void __cdecl Hazel::OpenGLShader::Complie(const class std::unordered_map<unsigned int,class std::basic_string<char,struct std::char_traits<char>,class std::allocator<char> >,struct std::hash<unsigned int>,struct std::equal_to<unsigned int>,class std::allocator<struct std::pair<unsigned int const ,class std::basic_string<char,struct std::char_traits<char>,class std::allocator<char> > > > > &)","ph":"X","pid":0,"tid":1130835890,"ts":41942087135},{"cat":"function","dur":32465,"name":"__cdecl Hazel::OpenGLShader::OpenGLShader(const class std::basic_string<char,struct std::char_traits<char>,class std::allocator<char> > &)","ph":"X","pid":0,"tid":1130835890,"ts":41942086956},{"cat":"function","dur":33686,"name":"void __cdecl Hazel::Renderer2D::Init(void)","ph":"X","pid":0,"tid":1130835890,"ts":41942085779},{"cat":"function","dur":891,"name":"void __cdecl Hazel::ImGuiLayer::OnAttach(void)","ph":"X","pid":0,"tid":1130835890,"ts":41942119490},{"cat":"function","dur":927,"name":"void __cdecl Hazel::Application::PushOverlay(class Hazel::Layer *)","ph":"X","pid":0,"tid":1130835890,"ts":41942119486},{"cat":"function","dur":2,"name":"__cdecl Hazel::OrthographicCamera::OrthographicCamera(float,float,float,float)","ph":"X","pid":0,"tid":1130835890,"ts":41942120438},{"cat":"function","dur":0,"name":"__cdecl Hazel::OrthographicCameraController::OrthographicCameraController(float,bool)","ph":"X","pid":0,"tid":1130835890,"ts":41942120459},{"cat":"function","dur":133,"name":"stbi_load - OpenGLTexture2D::OpenGlTexture2D(const std::string&)","ph":"X","pid":0,"tid":1130835890,"ts":41942120533},{"cat":"function","dur":179,"name":"__cdecl Hazel::OpenGLTexture2D::OpenGLTexture2D(const class std::basic_string<char,struct std::char_traits<char>,class std::allocator<char> > &)","ph":"X","pid":0,"tid":1130835890,"ts":41942120533},{"cat":"function","dur":429,"name":"stbi_load - OpenGLTexture2D::OpenGlTexture2D(const std::string&)","ph":"X","pid":0,"tid":1130835890,"ts":41942120736},{"cat":"function","dur":532,"name":"__cdecl Hazel::OpenGLTexture2D::OpenGLTexture2D(const class std::basic_string<char,struct std::char_traits<char>,class std::allocator<char> > &)","ph":"X","pid":0,"tid":1130835890,"ts":41942120736},{"cat":"function","dur":837,"name":"void __cdecl Hazel::EditorLayer::OnAttach(void)","ph":"X","pid":0,"tid":1130835890,"ts":41942120530},{"cat":"function","dur":877,"name":"void __cdecl Hazel::Application::PushLayer(class Hazel::Layer *)","ph":"X","pid":0,"tid":1130835890,"ts":41942120526}]}